hanzo_iam-1.29.0.dist-info/licenses/LICENSE
iam/__init__.py
iam/adapter.py
iam/application.py
iam/async_main.py
iam/cert.py
iam/enforcer.py
iam/group.py
iam/main.py
iam/model.py
iam/organization.py
iam/payment.py
iam/permission.py
iam/plan.py
iam/pricing.py
iam/product.py
iam/provider.py
iam/resource.py
iam/role.py
iam/session.py
iam/subscription.py
iam/syncer.py
iam/token.py
iam/user.py
iam/webhook.py
hanzo_iam-1.29.0.dist-info/METADATA
hanzo_iam-1.29.0.dist-info/WHEEL
hanzo_iam-1.29.0.dist-info/top_level.txt
hanzo_iam-1.29.0.dist-info/RECORD
