Metadata-Version: 2.4
Name: hanzo-iam
Version: 1.29.0
Summary: Python SDK built for IAM
Home-page: https://github.com/hanzoai/iam-python-sdk
Author: WooBin
Author-email: IAM <wbin90620@gmail.com>
License: Apache-2.0
Project-URL: Home, https://github.com/hanzoai/iam-python-sdk
Keywords: IAM
Platform: any
Classifier: Programming Language :: Python :: 3
Classifier: License :: OSI Approved :: Apache Software License
Classifier: Operating System :: OS Independent
Requires-Python: >=3.7
License-File: LICENSE
Requires-Dist: requests>=2.31.0
Requires-Dist: pyjwt>=2.8.0
Requires-Dist: cryptography>=41.0.7
Requires-Dist: aiohttp>=3.9.1
Dynamic: license-file
